Workbook

Sheet Dashboard_Overview
A1: EXECUTIVE SALES INTELLIGENCE DASHBOARD
A3: Dataset sintetico generato per validazione e benchmark agenti AI (Business Intelligence & Analytics)
B5: FATTURATO NETTO TOTALE | D5: MARGINE LORDO TOTALE | F5: MARGINALITÀ MEDIA PONDERATA
B6: =SUM(Transazioni_Vendite!N2:N251) | D6: =SUM(Transazioni_Vendite!Q2:Q251) | F6: =D6/B6
B9: Riepilogo per Categoria di Prodotto
B10: Categoria Prodotto | C10: Fatturato Netto (€) | D10: Margine Lordo (€) | E10: Margine % | F10: % su Fatturato Totale
B11: Cloud & Software | C11: =SUMIF(Transazioni_Vendite!$G$2:$G$251, B11, Transazioni_Vendite!$N$2:$N$251) | D11: =SUMIF(Transazioni_Vendite!$G$2:$G$251, B11, Transazioni_Vendite!$Q$2:$Q$251) | E11: =D11/C11 | F11: =C11/$B$6
B12: Hardware & IoT | C12: =SUMIF(Transazioni_Vendite!$G$2:$G$251, B12, Transazioni_Vendite!$N$2:$N$251) | D12: =SUMIF(Transazioni_Vendite!$G$2:$G$251, B12, Transazioni_Vendite!$Q$2:$Q$251) | E12: =D12/C12 | F12: =C12/$B$6
B13: Consulenza & Setup | C13: =SUMIF(Transazioni_Vendite!$G$2:$G$251, B13, Transazioni_Vendite!$N$2:$N$251) | D13: =SUMIF(Transazioni_Vendite!$G$2:$G$251, B13, Transazioni_Vendite!$Q$2:$Q$251) | E13: =D13/C13 | F13: =C13/$B$6

Sheet Transazioni_Vendite
A1: ID Transazione | B1: Data Ordine | C1: Canale | D1: Area Geografica | E1: Agente Vendite | F1: Segmento Cliente | G1: Categoria Prodotto | H1: SKU / Articolo | I1: Prezzo Unitario (€) | J1: Quantità | K1: Sconto Applicato (%) | L1: Fatturato Lordo (€) | M1: Importo Sconto (€) | N1: Fatturato Netto (€) | O1: Costo Unitario (€) | P1: Costo Totale (€) | Q1: Margine Lordo (€) | R1: Margine %
A2: TRX-2025-0001 | B2: 2025-02-09 | C2: E-commerce | D2: Nord-Est | E2: Giulia Bianchi | F2: Enterprise | G2: Cloud & Software | H2: SaaS-CORE-SMB | I2: 450 | J2: 5 | K2: 0.15 | L2: =I2*J2 | M2: =L2*K2 | N2: =L2-M2 | O2: 110 | P2: =O2*J2 | Q2: =N2-P2 | R2: =Q2/N2
A3: TRX-2025-0002 | B3: 2026-03-23 | C3: B2B Diretto | D3: Nord-Ovest | E3: Giulia Bianchi | F3: Enterprise | G3: Cloud & Software | H3: SaaS-PLATFORM-ENT | I3: 1200 | J3: 3 | K3: 0.1 | L3: =I3*J3 | M3: =L3*K3 | N3: =L3-M3 | O3: 320 | P3: =O3*J3 | Q3: =N3-P3 | R3: =Q3/N3
A4: TRX-2026-0003 | B4: 2025-08-28 | C4: B2B Diretto | D4: Centro | E4: Marco Rossi | F4: Professionisti / SOHO | G4: Cloud & Software | H4: AI-AGENT-MODULE | I4: 750 | J4: 5 | K4: 0 | L4: =I4*J4 | M4: =L4*K4 | N4: =L4-M4 | O4: 180 | P4: =O4*J4 | Q4: =N4-P4 | R4: =Q4/N4
A5: TRX-2025-0004 | B5: 2025-08-23 | C5: Partner / Retailer | D5: Centro | E5: Marco Rossi | F5: Enterprise | G5: Cloud & Software | H5: SaaS-CORE-SMB | I5: 450 | J5: 2 | K5: 0 | L5: =I5*J5 | M5: =L5*K5 | N5: =L5-M5 | O5: 110 | P5: =O5*J5 | Q5: =N5-P5 | R5: =Q5/N5
A6: TRX-2026-0005 | B6: 2025-02-28 | C6: E-commerce | D6: Estero (EU) | E6: Marco Rossi | F6: Pubblica Amministrazione | G6: Consulenza & Setup | H6: SETUP-INTEGRATION | I6: 1500 | J6: 1 | K6: 0 | L6: =I6*J6 | M6: =L6*K6 | N6: =L6-M6 | O6: 650 | P6: =O6*J6 | Q6: =N6-P6 | R6: =Q6/N6
A7: TRX-2026-0006 | B7: 2026-08-29 | C7: B2B Diretto | D7: Nord-Ovest | E7: Marco Rossi | F7: PMI | G7: Hardware & IoT | H7: SENSOR-IOT-PACK | I7: 290 | J7: 20 | K7: 0.15 | L7: =I7*J7 | M7: =L7*K7 | N7: =L7-M7 | O7: 140 | P7: =O7*J7 | Q7: =N7-P7 | R7: =Q7/N7
A8: TRX-2025-0007 | B8: 2026-02-08 | C8: B2B Diretto | D8: Centro | E8: Giulia Bianchi | F8: PMI | G8: Hardware & IoT | H8: GATEWAY-EDGE-PRO | I8: 890 | J8: 5 | K8: 0.1 | L8: =I8*J8 | M8: =L8*K8 | N8: =L8-M8 | O8: 520 | P8: =O8*J8 | Q8: =N8-P8 | R8: =Q8/N8
A9: TRX-2025-0008 | B9: 2025-07-09 | C9: E-commerce | D9: Nord-Est | E9: Giulia Bianchi | F9: PMI | G9: Hardware & IoT | H9: SENSOR-IOT-PACK | I9: 290 | J9: 20 | K9: 0.05 | L9: =I9*J9 | M9: =L9*K9 | N9: =L9-M9 | O9: 140 | P9: =O9*J9 | Q9: =N9-P9 | R9: =Q9/N9
A10: TRX-2025-0009 | B10: 2025-12-13 | C10: Partner / Retailer | D10: Nord-Ovest | E10: Giulia Bianchi | F10: Professionisti / SOHO | G10: Hardware & IoT | H10: TERMINAL-SMART-V2 | I10: 640 | J10: 2 | K10: 0 | L10: =I10*J10 | M10: =L10*K10 | N10: =L10-M10 | O10: 380 | P10: =O10*J10 | Q10: =N10-P10 | R10: =Q10/N10
A11: TRX-2026-0010 | B11: 2025-08-20 | C11: E-commerce | D11: Sud & Isole | E11: Elena Conti | F11: Enterprise | G11: Cloud & Software | H11: AI-AGENT-MODULE | I11: 750 | J11: 1 | K11: 0.05 | L11: =I11*J11 | M11: =L11*K11 | N11: =L11-M11 | O11: 180 | P11: =O11*J11 | Q11: =N11-P11 | R11: =Q11/N11
A12: TRX-2026-0011 | B12: 2026-03-29 | C12: Partner / Retailer | D12: Sud & Isole | E12: Alessandro Riva | F12: Enterprise | G12: Cloud & Software | H12: AI-AGENT-MODULE | I12: 750 | J12: 3 | K12: 0 | L12: =I12*J12 | M12: =L12*K12 | N12: =L12-M12 | O12: 180 | P12: =O12*J12 | Q12: =N12-P12 | R12: =Q12/N12
A13: TRX-2025-0012 | B13: 2025-05-07 | C13: B2B Diretto | D13: Nord-Est | E13: Elena Conti | F13: PMI | G13: Consulenza & Setup | H13: SETUP-INTEGRATION | I13: 1500 | J13: 2 | K13: 0.2 | L13: =I13*J13 | M13: =L13*K13 | N13: =L13-M13 | O13: 650 | P13: =O13*J13 | Q13: =N13-P13 | R13: =Q13/N13
... A251: TRX-2026-0250 | B251: 2025-10-05 | C251: E-commerce | D251: Sud & Isole | E251: Elena Conti | F251: PMI | G251: Hardware & IoT | H251: TERMINAL-SMART-V2 | I251: 640 | J251: 1 | K251: 0.1 | L251: =I251*J251 | M251: =L251*K251 | N251: =L251-M251 | O251: 380 | P251: =O251*J251 | Q251: =N251-P251 | R251: =Q251/N251

Sheet Budget_Target_2026
A1: Area / Agente | B1: Target Fatturato Netto 2025 (€) | C1: Target Fatturato Netto 2026 (€) | D1: Margine Minimo Obiettivo (%) | E1: Note Strategiche
A2: Marco Rossi | B2: 180000 | C2: 220000 | D2: 0.45 | E2: Focus espansione Enterprise Nord-Ovest
A3: Giulia Bianchi | B3: 160000 | C3: 200000 | D3: 0.48 | E3: Sviluppo canale SaaS Nord-Est
A4: Alessandro Riva | B4: 150000 | C4: 180000 | D4: 0.42 | E4: Presidio Pubblica Amministrazione Centro
A5: Elena Conti | B5: 140000 | C5: 175000 | D5: 0.5 | E5: Crescita servizi AI e Consulting Sud
A6: Roberto Moretti | B6: 200000 | C6: 260000 | D6: 0.46 | E6: Espansione partner commerciali Estero (EU)

Sheet Benchmark_Test_AI
A1: SUITE DI TEST E BENCHMARK PER AGENTE AI (BI & MATH ANALYSIS)
A3: Test ID | B3: Livello Complessità | C3: Area di Analisi | D3: Prompt / Domanda da sottoporre all'Agente | E3: Output Atteso / Metriche da Calcolare | F3: Tipo di Grafico Richiesto
A5: TEST-01 | B5: Base | C5: Aggregazione & KPI | D5: Analizza il foglio 'Transazioni_Vendite' e calcola: fatturato lordo totale, totale sconti concessi, fatturato netto finale e marginalità media complessiva. | E5: 4 valori scalari precisi (somme e % ponderata). Verifica se l'agente sa sommare formule o calcolare direttamente dai dati grezzi. | F5: Nessuno (output tabellare sintetico o bullet point)
A6: TEST-02 | B6: Intermedio | C6: Segmentazione per Canale | D6: Estrai la distribuzione percentuale del Fatturato Netto tra i tre canali (B2B Diretto, E-commerce, Partner / Retailer) e genera un grafico a torta o donut. | E6: Tabella pivot Canale -> Fatturato Netto, % su Totale. Generazione file immagine/HTML con grafico a torta coerente. | F6: Grafico a torta (Pie Chart) o Donut Chart
A7: TEST-03 | B7: Avanzato | C7: Performance Agenti vs Target | D7: Incrocia i dati delle vendite nette effettive realizzate da ciascun agente con il foglio 'Budget_Target_2026'. Chi ha raggiunto o superato il target 2025? Qual è il gap percentuale? | E7: Calcolo del fatturato netto per agente per l'anno 2025 (filtrando la data), confronto con colonna B del foglio Target, calcolo Delta (€) e % raggiungimento. | F7: Grafico a barre orizzontali / clustered bar con confronto Target vs Effettivo
A8: TEST-04 | B8: Avanzato | C8: Trend Temporale & Run-Rate | D8: Raggruppa il fatturato netto su base mensile dal 2025 al 2026. Calcola il Month-over-Month growth rate (MoM) e genera un grafico a linee con evidenziata la media mobile a 3 mesi. | E8: Time-series mensile (es. 2025-01, 2025-02...), calcolo MoM [(M_t - M_{t-1})/M_{t-1}], serie media mobile 3M. | F8: Grafico a linee (Line Chart) con 2 serie (Fatturato Mensile + Media Mobile)
A9: TEST-05 | B9: Complesso / BI | C9: Redditività per SKU & Scontistica | D9: Qual è l'impatto degli sconti applicati sul margine percentuale? Mostrami una correlazione o raggruppamento per fascia di sconto (0%, 5%, 10%, 15%, 20%) con margine medio e volume venduto. | E9: Tabella per classe di sconto: N° transazioni, Margine medio %, Fatturato medio. Analisi quantitativa dell'elasticità/erosione del margine. | F9: Grafico combinato Barre (Volumi) + Linea (Margine % medio) o Scatter plot
A10: TEST-06 | B10: Complesso / Python Code | C10: Analisi di Pareto (80/20) | D10: Esegui un'analisi di Pareto sui prodotti (SKU): identifica quali articoli generano l'80% del fatturato netto complessivo e genera il relativo grafico di Pareto. | E10: Classifica decrescente per fatturato, calcolo % cumulata, evidenziazione soglia 80%. | F10: Diagramma di Pareto (Barre decrescenti + linea curva cumulata)
